vsstg/__init__.py
vsstg/__main__.py
vsstg/_metadata.py
vsstg/init.py
vsstg-3.0.1.dist-info/LICENSE
vsstg-3.0.1.dist-info/METADATA
vsstg-3.0.1.dist-info/WHEEL
vsstg-3.0.1.dist-info/entry_points.txt
vsstg-3.0.1.dist-info/top_level.txt
vsstg-3.0.1.dist-info/RECORD
