Metadata-Version: 2.1
Name: vsstg
Version: 3.0.1
Summary: VapourSynth packages from Setsugennoao
Author: Irrational Encoding Wizardry
Author-email: wizards@encode.moe
Maintainer: Setsugen no ao
Maintainer-email: setsugen@setsugen.dev
Project-URL: Source Code, https://github.com/Setsugennoao
Project-URL: Contact, https://discord.gg/setsugen
Classifier: Programming Language :: Python :: 3
Classifier: License :: OSI Approved :: MIT License
Classifier: Operating System :: OS Independent
Requires-Python: >=3.11
License-File: LICENSE
Requires-Dist: VapourSynth >=65
Requires-Dist: vstools ==3.0.0
Requires-Dist: vspyplugin ==1.4.0
Requires-Dist: vskernels ==3.0.1
Requires-Dist: vsexprtools ==1.5.0
Requires-Dist: vsrgtools ==1.6.1
Requires-Dist: vsmasktools ==1.2.0
Requires-Dist: vsaa ==1.9.0
Requires-Dist: vsscale ==2.0.0
Requires-Dist: vsdenoise ==2.5.0
Requires-Dist: vsdehalo ==1.8.0
Requires-Dist: vsdeband ==1.1.0
Requires-Dist: vsdeinterlace ==0.6.0
Requires-Dist: vssource ==0.9.6
Requires-Dist: vspreview ==0.8.0
